{
	"artificer": {
		"dir_count": 1,
		"width": 32,
		"height": 32,
		"dirs": {
			"2": {
				"frames": [
					{
						"x": 0,
						"y": 0,
						"delay": 100
					}
				]
			}
		},
		"tile_size": 32
	},
	"summonsoulstone": {
		"dir_count": 1,
		"width": 32,
		"height": 32,
		"dirs": {
			"2": {
				"frames": [
					{
						"x": 32,
						"y": 0,
						"delay": 100
					}
				]
			}
		},
		"tile_size": 32
	},
	"cult_comms": {
		"dir_count": 1,
		"width": 32,
		"height": 32,
		"dirs": {
			"2": {
				"frames": [
					{
						"x": 64,
						"y": 0,
						"delay": 100
					}
				]
			}
		},
		"tile_size": 32
	},
	"cultforcewall": {
		"dir_count": 1,
		"width": 32,
		"height": 32,
		"dirs": {
			"2": {
				"frames": [
					{
						"x": 96,
						"y": 0,
						"delay": 100
					}
				]
			}
		},
		"tile_size": 32
	},
	"telerune": {
		"dir_count": 1,
		"width": 32,
		"height": 32,
		"dirs": {
			"2": {
				"frames": [
					{
						"x": 0,
						"y": 32,
						"delay": 100
					}
				]
			}
		},
		"tile_size": 32
	},
	"phaseshift": {
		"dir_count": 1,
		"width": 32,
		"height": 32,
		"dirs": {
			"2": {
				"frames": [
					{
						"x": 32,
						"y": 32,
						"delay": 100
					}
				]
			}
		},
		"tile_size": 32
	},
	"lesserconstruct": {
		"dir_count": 1,
		"width": 32,
		"height": 32,
		"dirs": {
			"2": {
				"frames": [
					{
						"x": 64,
						"y": 32,
						"delay": 100
					}
				]
			}
		},
		"tile_size": 32
	},
	"floorconstruct": {
		"dir_count": 1,
		"width": 32,
		"height": 32,
		"dirs": {
			"2": {
				"frames": [
					{
						"x": 96,
						"y": 32,
						"delay": 100
					}
				]
			}
		},
		"tile_size": 32
	},
	"areaconvert": {
		"dir_count": 1,
		"width": 32,
		"height": 32,
		"dirs": {
			"2": {
				"frames": [
					{
						"x": 0,
						"y": 64,
						"delay": 100
					}
				]
			}
		},
		"tile_size": 32
	},
	"cultvote": {
		"dir_count": 1,
		"width": 32,
		"height": 32,
		"dirs": {
			"2": {
				"frames": [
					{
						"x": 32,
						"y": 64,
						"delay": 100
					}
				]
			}
		},
		"tile_size": 32
	},
	"abyssal_gaze": {
		"dir_count": 1,
		"width": 32,
		"height": 32,
		"dirs": {
			"2": {
				"frames": [
					{
						"x": 64,
						"y": 64,
						"delay": 100
					}
				]
			}
		},
		"tile_size": 32
	},
	"dominate": {
		"dir_count": 1,
		"width": 32,
		"height": 32,
		"dirs": {
			"2": {
				"frames": [
					{
						"x": 96,
						"y": 64,
						"delay": 100
					}
				]
			}
		},
		"tile_size": 32
	},
	"cult_mark": {
		"dir_count": 1,
		"width": 32,
		"height": 32,
		"dirs": {
			"2": {
				"frames": [
					{
						"x": 0,
						"y": 96,
						"delay": 100
					}
				]
			}
		},
		"tile_size": 32
	},
	"sintouch": {
		"dir_count": 1,
		"width": 32,
		"height": 32,
		"dirs": {
			"2": {
				"frames": [
					{
						"x": 32,
						"y": 96,
						"delay": 100
					}
				]
			}
		},
		"tile_size": 32
	}
}